Workbook

Sheet Lançamentos
A1: Bevel — Fluxo de caixa (entradas e saídas)
A2: Azul = dado digitado · Amarelo = falta preencher · Saldo só conta o que é Realizado e da Empresa. Datas marcadas 'Não' em 'Data exata?' são aproximadas.
A4: Data | B4: Data exata? | C4: Tipo | D4: Descrição | E4: Categoria | F4: Quem pagou / onde caiu | G4: Valor (R$) | H4: Status | I4: Conta da empresa? | J4: Saldo acumulado realizado (R$) | K4: Observação / fonte
A5: 46267 | B5: Sim | C5: Entrada | D5: Gabe — 1ª parcela (parte 1) | E5: Cliente | F5: Conta pessoal do Arthur | G5: 178.75 | H5: Realizado | I5: Sim | J5: =0+IF(AND(H5="Realizado",I5="Sim"),IF(C5="Entrada",1,-1)*N(G5),0) | K5: Contrato assinado; regularizar repasse
A6: 46290 | B6: Sim | C6: Entrada | D6: Gabe — 1ª parcela (parte 2) | E6: Cliente | F6: A confirmar | G6: 178.75 | H6: Realizado | I6: Sim | J6: =J5+IF(AND(H6="Realizado",I6="Sim"),IF(C6="Entrada",1,-1)*N(G6),0) | K6: ClickUp: pagamento confirmado em 27/09
A7: 46292 | B7: Não | C7: Saída | D7: Playbook (mensalidade) | E7: Ferramenta | F7: Cartão Lucas | G7: 29.9 | H7: Realizado | I7: Sim | J7: =J6+IF(AND(H7="Realizado",I7="Sim"),IF(C7="Entrada",1,-1)*N(G7),0) | K7: Rateio out/2026 (Zé). Data = fechamento da fatura paga em 10/10
A8: 46292 | B8: Não | C8: Saída | D8: Tokens | E8: IA / API | F8: Cartão Lucas | G8: 74.77 | H8: Realizado | I8: Sim | J8: =J7+IF(AND(H8="Realizado",I8="Sim"),IF(C8="Entrada",1,-1)*N(G8),0) | K8: Rateio out/2026 (Zé). Data = fechamento da fatura
A9: 46292 | B9: Não | C9: Saída | D9: Chips pré-pagos (3 números) | E9: Telefonia | F9: Arthur | G9: 90 | H9: Realizado | I9: Sim | J9: =J8+IF(AND(H9="Realizado",I9="Sim"),IF(C9="Entrada",1,-1)*N(G9),0) | K9: Rateio out/2026; na planilha antiga aparece como custo de agosto
A10: 46292 | B10: Não | C10: Saída | D10: Chip pré-pago (1 número) | E10: Telefonia | F10: Vitor | G10: 35 | H10: Realizado | I10: Sim | J10: =J9+IF(AND(H10="Realizado",I10="Sim"),IF(C10="Entrada",1,-1)*N(G10),0) | K10: Rateio out/2026; na planilha antiga aparece como custo de agosto
A11: 46292 | B11: Não | C11: Saída | D11: Claude — Zé | E11: Assinatura | F11: Cartão Lucas (Arthur reembolsa) | G11: 110 | H11: Realizado | I11: Não | J11: =J10+IF(AND(H11="Realizado",I11="Sim"),IF(C11="Entrada",1,-1)*N(G11),0) | K11: Regra atual: cada sócio paga o próprio Claude
A12: 46292 | B12: Não | C12: Saída | D12: Claude — VT | E12: Assinatura | F12: Cartão Lucas (Vitor reembolsa) | G12: 110 | H12: Realizado | I12: Não | J12: =J11+IF(AND(H12="Realizado",I12="Sim"),IF(C12="Entrada",1,-1)*N(G12),0) | K12: Regra atual: cada sócio paga o próprio Claude
A13: 46294 | B13: Não | C13: Saída | D13: Créditos API Gemini | E13: IA / API | F13: A confirmar | H13: Realizado | I13: Sim | J13: =J12+IF(AND(H13="Realizado",I13="Sim"),IF(C13="Entrada",1,-1)*N(G13),0) | K13: ClickUp 'Adicionar dinheiro do Gemini' concluída ~29/09; valor não registrado
A14: 46295 | B14: Não | C14: Saída | D14: Chip do Gabe | E14: Telefonia | F14: Arthur | H14: Realizado | I14: Sim | J14: =J13+IF(AND(H14="Realizado",I14="Sim"),IF(C14="Entrada",1,-1)*N(G14),0) | K14: ClickUp 'Comprar chip - Morais Barbershop' concluída ~30/09; valor não registrado
A15: 46315 | B15: Sim | C15: Entrada | D15: Gabe — 2ª parcela | E15: Cliente | F15: A definir | G15: 357.5 | H15: Previsto | I15: Sim | J15: =J14+IF(AND(H15="Realizado",I15="Sim"),IF(C15="Entrada",1,-1)*N(G15),0) | K15: Contrato
A16: 46322 | B16: Não | C16: Saída | D16: Custos do bot do Gabe (Gemini etc.) | E16: IA / API | F16: Cartão Lucas | H16: Previsto | I16: Sim | J16: =J15+IF(AND(H16="Realizado",I16="Sim"),IF(C16="Entrada",1,-1)*N(G16),0) | K16: Entra na fatura que fecha 27/10 e vence 10/11
A17: 46346 | B17: Sim | C17: Entrada | D17: Gabe — 3ª parcela | E17: Cliente | F17: A definir | G17: 357.5 | H17: Previsto | I17: Sim | J17: =J16+IF(AND(H17="Realizado",I17="Sim"),IF(C17="Entrada",1,-1)*N(G17),0) | K17: Contrato
A18: 46376 | B18: Sim | C18: Entrada | D18: Gabe — 4ª parcela | E18: Cliente | F18: A definir | G18: 357.5 | H18: Previsto | I18: Sim | J18: =J17+IF(AND(H18="Realizado",I18="Sim"),IF(C18="Entrada",1,-1)*N(G18),0) | K18: Contrato
A19: 46376 | B19: Não | C19: Entrada | D19: Gabe — 1ª mensalidade de manutenção | E19: Cliente | F19: A definir | G19: 119 | H19: Previsto | I19: Sim | J19: =J18+IF(AND(H19="Realizado",I19="Sim"),IF(C19="Entrada",1,-1)*N(G19),0) | K19: ≈10% de R$ 1.190 — confirmar base no contrato; pode ser renegociada

Sheet Resumo
A1: Resumo
A3: Entradas realizadas | B3: =SUMIFS('Lançamentos'!$G$5:$G$200,'Lançamentos'!$C$5:$C$200,"Entrada",'Lançamentos'!$H$5:$H$200,"Realizado",'Lançamentos'!$I$5:$I$200,"Sim")
A4: Saídas realizadas (empresa) | B4: =SUMIFS('Lançamentos'!$G$5:$G$200,'Lançamentos'!$C$5:$C$200,"Saída",'Lançamentos'!$H$5:$H$200,"Realizado",'Lançamentos'!$I$5:$I$200,"Sim")
A5: Saldo realizado (empresa) | B5: =B3-B4
A7: Claude pago pelos sócios (fora do saldo) | B7: =SUMIFS('Lançamentos'!$G$5:$G$200,'Lançamentos'!$C$5:$C$200,"Saída",'Lançamentos'!$I$5:$I$200,"Não")
A8: Saldo se Claude fosse da empresa | B8: =B5-B7
A10: Entradas previstas | B10: =SUMIFS('Lançamentos'!$G$5:$G$200,'Lançamentos'!$C$5:$C$200,"Entrada",'Lançamentos'!$H$5:$H$200,"Previsto")
A11: Saídas previstas (valores conhecidos) | B11: =SUMIFS('Lançamentos'!$G$5:$G$200,'Lançamentos'!$C$5:$C$200,"Saída",'Lançamentos'!$H$5:$H$200,"Previsto")
A12: Saldo projetado até dez/2026 | B12: =B5+B10-B11
A14: Lançamentos sem valor (preencher) | B14: =COUNTIFS('Lançamentos'!$D$5:$D$200,"<>",'Lançamentos'!$G$5:$G$200,"")
A17: Saldo projetado não inclui custos ainda sem valor (bot do Gabe, Gemini, chip do Gabe, servidor).
